{
      "list": [{
                  "id": "2013212743",
                  "name": "马超",
                  "class": "软工132",
                  "page": "http://xiliangjinmachao.github.io/",
                  "call1": "1",
                  "call2": "1",
                  "work1": "0",
                  "work2": "0",
                  "work3": "0",
                  "work4": "0",
                  "work5": "0",
                  "work6": "0"
            }, {
                  "id": "2014211131",
                  "name": "乐佳琨",
                  "class": "软工141",
                  "page": "https://ljk1521152923.github.io/",
                  "call1": "0",
                  "call2": "0",
                  "work1": "0",
                  "work2": "0",
                  "work3": "0",
                  "work4": "0",
                  "work5": "0",
                  "work6": "0"
            }, {
                  "id": "2015210402032",
                  "name": "许承瑶",
                  "class": "计算机153",
                  "page": "https://xuchengyao.github.io/XCY/",
                  "call1": "1",
                  "call2": "1",
                  "work1": "80",
                  "work2": "60",
                  "work3": "80",
                  "work4": "80",
                  "work5": "60",
                  "work6": "60"
            }, {
                  "id": "2015210402033",
                  "name": "刘庆",
                  "class": "计算机153",
                  "page": "https://lliuqing.github.io/liuqing.github.com/",
                  "call1": "1",
                  "call2": "1",
                  "work1": "60",
                  "work2": "60",
                  "work3": "80",
                  "work4": "60",
                  "work5": "60",
                  "work6": "60"
            }, {
                  "id": "2015210402041",
                  "name": "方柯",
                  "class": "计算机153",
                  "page": "http:// https://1450688781.github.io/",
                  "call1": "0",
                  "call2": "0",
                  "work1": "0",
                  "work2": "0",
                  "work3": "0",
                  "work4": "0",
                  "work5": "0",
                  "work6": "0"
            }, {
                  "id": "2015210402086",
                  "name": "陆紫涵",
                  "class": "计算机153",
                  "page": "https://lzhishere.github.io/w/",
                  "call1": "0",
                  "call2": "0",
                  "work1": "90",
                  "work2": "80",
                  "work3": "60",
                  "work4": "80",
                  "work5": "80",
                  "work6": "0"
            }, {
                  "id": "2015210402102",
                  "name": "陈雨露",
                  "class": "计算机153",
                  "page": "http://chenyvluinweb.github.io/",
                  "call1": "0",
                  "call2": "0",
                  "work1": "70",
                  "work2": "80",
                  "work3": "0",
                  "work4": "0",
                  "work5": "0",
                  "work6": "0"
            }, {
                  "id": "2015210405001",
                  "name": "蔡澄捷",
                  "class": "软工151",
                  "page": "https://chengjiec1997.github.io/",
                  "call1": "0",
                  "call2": "1",
                  "work1": "80",
                  "work2": "70",
                  "work3": "70",
                  "work4": "90",
                  "work5": "90",
                  "work6": "80"
            }, {
                  "id": "2015210405002",
                  "name": "郑嘉逸",
                  "class": "软工151",
                  "page": "http://g11997.github.io",
                  "call1": "1",
                  "call2": "1",
                  "work1": "90",
                  "work2": "80",
                  "work3": "70",
                  "work4": "90",
                  "work5": "85",
                  "work6": "90"
            }, {
                  "id": "2015210405003",
                  "name": "徐韬",
                  "class": "软工151",
                  "page": "http://duskcloudxu.github.io/",
                  "call1": "1",
                  "call2": "1",
                  "work1": "90",
                  "work2": "80",
                  "work3": "90",
                  "work4": "95",
                  "work5": "95",
                  "work6": "80"
            }, {
                  "id": "2015210405004",
                  "name": "吴际",
                  "class": "软工151",
                  "page": "https://2015210405004.github.io/",
                  "call1": "1",
                  "call2": "1",
                  "work1": "70",
                  "work2": "70",
                  "work3": "80",
                  "work4": "95",
                  "work5": "80",
                  "work6": "70"
            }, {
                  "id": "2015210405005",
                  "name": "吕靖之",
                  "class": "软工151",
                  "page": "https://lvjingzhi.github.io/",
                  "call1": "0",
                  "call2": "1",
                  "work1": "90",
                  "work2": "80",
                  "work3": "80",
                  "work4": "60",
                  "work5": "60",
                  "work6": "60"
            }, {
                  "id": "2015210405006",
                  "name": "全琪",
                  "class": "软工151",
                  "page": "https://quanqi1997.github.io/",
                  "call1": "1",
                  "call2": "1",
                  "work1": "80",
                  "work2": "70",
                  "work3": "60",
                  "work4": "60",
                  "work5": "60",
                  "work6": "60"
            }, {
                  "id": "2015210405007",
                  "name": "袁宵月",
                  "class": "软工151",
                  "page": "https://yuanxiaoyue.github.io/",
                  "call1": "1",
                  "call2": "1",
                  "work1": "90",
                  "work2": "70",
                  "work3": "80",
                  "work4": "90",
                  "work5": "70",
                  "work6": "85"
            }, {
                  "id": "2015210405008",
                  "name": "马港楠",
                  "class": "软工151",
                  "page": "https://nankanull.github.io",
                  "call1": "1",
                  "call2": "1",
                  "work1": "80",
                  "work2": "90",
                  "work3": "70",
                  "work4": "90",
                  "work5": "90",
                  "work6": "90"
            }, {
                  "id": "2015210405010",
                  "name": "吴燕波",
                  "class": "软工151",
                  "page": "http://wyb518.github.io/",
                  "call1": "1",
                  "call2": "1",
                  "work1": "70",
                  "work2": "70",
                  "work3": "60",
                  "work4": "90",
                  "work5": "85",
                  "work6": "80"
            }, {
                  "id": "2015210405011",
                  "name": "洪磊",
                  "class": "软工151",
                  "page": "http://hldadiao.github.io",
                  "call1": "1",
                  "call2": "1",
                  "work1": "60",
                  "work2": "70",
                  "work3": "60",
                  "work4": "80",
                  "work5": "70",
                  "work6": "80"
            }, {
                  "id": "2015210405013",
                  "name": "岑焕亚",
                  "class": "软工151",
                  "page": "https://uniquec.github.io/",
                  "call1": "1",
                  "call2": "1",
                  "work1": "70",
                  "work2": "80",
                  "work3": "80",
                  "work4": "90",
                  "work5": "90",
                  "work6": "60"
            }, {
                  "id": "2015210405014",
                  "name": "虞哲",
                  "class": "软工151",
                  "page": "https://realityvibe.github.io/",
                  "call1": "1",
                  "call2": "1",
                  "work1": "90",
                  "work2": "80",
                  "work3": "90",
                  "work4": "80",
                  "work5": "80",
                  "work6": "80"
            }, {
                  "id": "2015210405017",
                  "name": "张晨昊",
                  "class": "软工151",
                  "page": "http://zchmix.github.io",
                  "call1": "0",
                  "call2": "1",
                  "work1": "70",
                  "work2": "70",
                  "work3": "70",
                  "work4": "60",
                  "work5": "60",
                  "work6": "60"
            }, {
                  "id": "2015210405018",
                  "name": "陈都",
                  "class": "软工151",
                  "page": "https://dlscindy.github.io",
                  "call1": "1",
                  "call2": "1",
                  "work1": "70",
                  "work2": "80",
                  "work3": "90",
                  "work4": "90",
                  "work5": "70",
                  "work6": "70"
            }, {
                  "id": "2015210405019",
                  "name": "林一凡",
                  "class": "软工151",
                  "page": "https://oceanapart.github.io/",
                  "call1": "1",
                  "call2": "1",
                  "work1": "95",
                  "work2": "95",
                  "work3": "95",
                  "work4": "90",
                  "work5": "90",
                  "work6": "85"
            }, {
                  "id": "2015210405020",
                  "name": "许沈恬",
                  "class": "软工151",
                  "page": "http://xsthhh.github.io",
                  "call1": "1",
                  "call2": "1",
                  "work1": "80",
                  "work2": "80",
                  "work3": "70",
                  "work4": "85",
                  "work5": "90",
                  "work6": "90"
            }, {
                  "id": "2015210405021",
                  "name": "赵渊悦",
                  "class": "软工151",
                  "page": "http://woshishouzi.github.io",
                  "call1": "1",
                  "call2": "1",
                  "work1": "90",
                  "work2": "80",
                  "work3": "80",
                  "work4": "80",
                  "work5": "80",
                  "work6": "85"
            }, {
                  "id": "2015210405022",
                  "name": "翁泽超",
                  "class": "软工151",
                  "page": "http://wengzechao.github.io",
                  "call1": "1",
                  "call2": "1",
                  "work1": "90",
                  "work2": "80",
                  "work3": "80",
                  "work4": "90",
                  "work5": "90",
                  "work6": "80"
            }, {
                  "id": "2015210405023",
                  "name": "沈季涛",
                  "class": "软工151",
                  "page": "https://umbrellamans.github.io/",
                  "call1": "1",
                  "call2": "1",
                  "work1": "60",
                  "work2": "70",
                  "work3": "80",
                  "work4": "80",
                  "work5": "80",
                  "work6": "80"
            }, {
                  "id": "2015210405024",
                  "name": "崔甜甜",
                  "class": "软工151",
                  "page": "https://ctt1997.github.io/",
                  "call1": "1",
                  "call2": "1",
                  "work1": "80",
                  "work2": "80",
                  "work3": "70",
                  "work4": "90",
                  "work5": "80",
                  "work6": "90"
            }, {
                  "id": "2015210405025",
                  "name": "俞天琪",
                  "class": "软工151",
                  "page": "http://lenayoga.github.io",
                  "call1": "1",
                  "call2": "1",
                  "work1": "90",
                  "work2": "80",
                  "work3": "80",
                  "work4": "80",
                  "work5": "85",
                  "work6": "85"
            }, {
                  "id": "2015210405026",
                  "name": "郭钰燕",
                  "class": "软工151",
                  "page": "http://colinaya.github.io/",
                  "call1": "1",
                  "call2": "1",
                  "work1": "80",
                  "work2": "80",
                  "work3": "80",
                  "work4": "90",
                  "work5": "80",
                  "work6": "90"
            }, {
                  "id": "2015210405027",
                  "name": "骆涵泽",
                  "class": "软工151",
                  "page": "http://doubleninejiujiu.github.io",
                  "call1": "1",
                  "call2": "1",
                  "work1": "70",
                  "work2": "70",
                  "work3": "70",
                  "work4": "90",
                  "work5": "70",
                  "work6": "80"
            }, {
                  "id": "2015210405028",
                  "name": "胡迪恒",
                  "class": "软工151",
                  "page": "http://smoothiefrog.github.io",
                  "call1": "1",
                  "call2": "1",
                  "work1": "70",
                  "work2": "70",
                  "work3": "70",
                  "work4": "90",
                  "work5": "80",
                  "work6": "95"
            }, {
                  "id": "2015210405029",
                  "name": "吕海涛",
                  "class": "软工151",
                  "page": "https://770288161.github.io",
                  "call1": "1",
                  "call2": "1",
                  "work1": "70",
                  "work2": "60",
                  "work3": "60",
                  "work4": "90",
                  "work5": "70",
                  "work6": "80"
            }, {
                  "id": "2015210405030",
                  "name": "吴倩倩",
                  "class": "软工151",
                  "page": "http://zhejiji.github.io",
                  "call1": "1",
                  "call2": "1",
                  "work1": "90",
                  "work2": "80",
                  "work3": "60",
                  "work4": "70",
                  "work5": "70",
                  "work6": "80"
            }, {
                  "id": "2015210405031",
                  "name": "王靖",
                  "class": "软工151",
                  "page": "http://wangjingaaa.github.io",
                  "call1": "0",
                  "call2": "1",
                  "work1": "80",
                  "work2": "80",
                  "work3": "60",
                  "work4": "70",
                  "work5": "80",
                  "work6": "80"
            }, {
                  "id": "2015210405032",
                  "name": "谢佳敏",
                  "class": "软工151",
                  "page": "https://xiejiamin.github.io/",
                  "call1": "1",
                  "call2": "1",
                  "work1": "80",
                  "work2": "85",
                  "work3": "80",
                  "work4": "85",
                  "work5": "90",
                  "work6": "80"
            }, {
                  "id": "2015210405033",
                  "name": "陈崇淇",
                  "class": "软工151",
                  "page": "http://ccq1233.github.io",
                  "call1": "1",
                  "call2": "1",
                  "work1": "60",
                  "work2": "70",
                  "work3": "60",
                  "work4": "80",
                  "work5": "80",
                  "work6": "90"
            }, {
                  "id": "2015210405034",
                  "name": "林亨泽",
                  "class": "软工151",
                  "page": "http://lhzslpr.github.io/",
                  "call1": "0",
                  "call2": "1",
                  "work1": "70",
                  "work2": "70",
                  "work3": "0",
                  "work4": "70",
                  "work5": "80",
                  "work6": "70"
            }, {
                  "id": "2015210405036",
                  "name": "周珍",
                  "class": "软工151",
                  "page": "http://zhouzh123.github.io",
                  "call1": "1",
                  "call2": "1",
                  "work1": "90",
                  "work2": "70",
                  "work3": "70",
                  "work4": "90",
                  "work5": "80",
                  "work6": "95"
            }, {
                  "id": "2015210405037",
                  "name": "傅杭波",
                  "class": "软工151",
                  "page": "https://fhb4062641.github.io/",
                  "call1": "1",
                  "call2": "1",
                  "work1": "70",
                  "work2": "80",
                  "work3": "90",
                  "work4": "90",
                  "work5": "90",
                  "work6": "90"
            }, {
                  "id": "2015210405038",
                  "name": "王议莹",
                  "class": "软工151",
                  "page": "https://nine-e.github.io",
                  "call1": "1",
                  "call2": "1",
                  "work1": "90",
                  "work2": "80",
                  "work3": "80",
                  "work4": "90",
                  "work5": "90",
                  "work6": "100"
            }, {
                  "id": "2015210405039",
                  "name": "李芸婷",
                  "class": "软工151",
                  "page": "http://roy33.github.io",
                  "call1": "1",
                  "call2": "1",
                  "work1": "80",
                  "work2": "80",
                  "work3": "80",
                  "work4": "90",
                  "work5": "80",
                  "work6": "70"
            }, {
                  "id": "2015210405040",
                  "name": "秦汉",
                  "class": "软工151",
                  "page": "http://qinhan2333.github.io/",
                  "call1": "0",
                  "call2": "1",
                  "work1": "90",
                  "work2": "80",
                  "work3": "60",
                  "work4": "80",
                  "work5": "70",
                  "work6": "80"
            }, {
                  "id": "2015210405041",
                  "name": "俞浩天",
                  "class": "软工152",
                  "page": "https://cloudyttt.github.io/",
                  "call1": "1",
                  "call2": "1",
                  "work1": "70",
                  "work2": "70",
                  "work3": "80",
                  "work4": "70",
                  "work5": "80",
                  "work6": "80"
            }, {
                  "id": "2015210405042",
                  "name": "王琛琪",
                  "class": "软工152",
                  "page": "https://juiceblue.github.io/",
                  "call1": "1",
                  "call2": "1",
                  "work1": "80",
                  "work2": "80",
                  "work3": "90",
                  "work4": "80",
                  "work5": "90",
                  "work6": "85"
            }, {
                  "id": "2015210405043",
                  "name": "林海瑞",
                  "class": "软工152",
                  "page": "https://lhralander.github.io",
                  "call1": "1",
                  "call2": "1",
                  "work1": "95",
                  "work2": "90",
                  "work3": "90",
                  "work4": "90",
                  "work5": "90",
                  "work6": "85"
            }, {
                  "id": "2015210405044",
                  "name": "陈颖兰",
                  "class": "软工152",
                  "page": "http://summer-cyl.github.io",
                  "call1": "1",
                  "call2": "1",
                  "work1": "85",
                  "work2": "80",
                  "work3": "95",
                  "work4": "90",
                  "work5": "90",
                  "work6": "80"
            }, {
                  "id": "2015210405045",
                  "name": "徐欣奕",
                  "class": "软工152",
                  "page": "http://mykepler.github.io",
                  "call1": "1",
                  "call2": "1",
                  "work1": "90",
                  "work2": "80",
                  "work3": "90",
                  "work4": "80",
                  "work5": "90",
                  "work6": "95"
            }, {
                  "id": "2015210405046",
                  "name": "章健伟",
                  "class": "软工152",
                  "page": "http://zk332.github.io",
                  "call1": "1",
                  "call2": "1",
                  "work1": "80",
                  "work2": "80",
                  "work3": "70",
                  "work4": "90",
                  "work5": "70",
                  "work6": "80"
            }, {
                  "id": "2015210405047",
                  "name": "戴雅婕",
                  "class": "软工152",
                  "page": "http://investgation.github.io",
                  "call1": "1",
                  "call2": "1",
                  "work1": "90",
                  "work2": "80",
                  "work3": "70",
                  "work4": "90",
                  "work5": "70",
                  "work6": "80"
            }, {
                  "id": "2015210405048",
                  "name": "翟健羽",
                  "class": "软工152",
                  "page": "http://zhaijianyu.github.io",
                  "call1": "1",
                  "call2": "1",
                  "work1": "80",
                  "work2": "60",
                  "work3": "60",
                  "work4": "60",
                  "work5": "70",
                  "work6": "70"
            }, {
                  "id": "2015210405049",
                  "name": "吴佳思",
                  "class": "软工152",
                  "page": "https://123just.github.io/",
                  "call1": "1",
                  "call2": "1",
                  "work1": "80",
                  "work2": "90",
                  "work3": "90",
                  "work4": "90",
                  "work5": "80",
                  "work6": "60"
            }, {
                  "id": "2015210405050",
                  "name": "周则张",
                  "class": "软工152",
                  "page": "http://664159586.github.io/",
                  "call1": "1",
                  "call2": "1",
                  "work1": "70",
                  "work2": "70",
                  "work3": "70",
                  "work4": "70",
                  "work5": "70",
                  "work6": "60"
            }, {
                  "id": "2015210405052",
                  "name": "夏吕丹",
                  "class": "软工152",
                  "page": "http://shadowlay.github.io",
                  "call1": "1",
                  "call2": "1",
                  "work1": "70",
                  "work2": "70",
                  "work3": "70",
                  "work4": "90",
                  "work5": "90",
                  "work6": "90"
            }, {
                  "id": "2015210405053",
                  "name": "詹罗梦甜",
                  "class": "软工152",
                  "page": "http://zhanlmt.github.io",
                  "call1": "1",
                  "call2": "1",
                  "work1": "90",
                  "work2": "85",
                  "work3": "60",
                  "work4": "0",
                  "work5": "70",
                  "work6": "90"
            }, {
                  "id": "2015210405054",
                  "name": "赵杭琪",
                  "class": "软工152",
                  "page": "http://zhq1516.github.io",
                  "call1": "1",
                  "call2": "1",
                  "work1": "70",
                  "work2": "70",
                  "work3": "70",
                  "work4": "80",
                  "work5": "90",
                  "work6": "80"
            }, {
                  "id": "2015210405055",
                  "name": "孔志鹏",
                  "class": "软工152",
                  "page": "https://kongzhipeng.github.io/",
                  "call1": "1",
                  "call2": "1",
                  "work1": "90",
                  "work2": "90",
                  "work3": "85",
                  "work4": "90",
                  "work5": "90",
                  "work6": "80"
            }, {
                  "id": "2015210405056",
                  "name": "李豪",
                  "class": "软工152",
                  "page": "https://ls1rius.github.io",
                  "call1": "1",
                  "call2": "1",
                  "work1": "80",
                  "work2": "85",
                  "work3": "90",
                  "work4": "80",
                  "work5": "80",
                  "work6": "80"
            }, {
                  "id": "2015210405057",
                  "name": "陈金才",
                  "class": "软工152",
                  "page": "http://CHENPaulJC.github.io",
                  "call1": "1",
                  "call2": "1",
                  "work1": "90",
                  "work2": "70",
                  "work3": "70",
                  "work4": "80",
                  "work5": "80",
                  "work6": "80"
            }, {
                  "id": "2015210405058",
                  "name": "林冬慧",
                  "class": "软工152",
                  "page": "https://leandh.github.io/",
                  "call1": "1",
                  "call2": "1",
                  "work1": "90",
                  "work2": "85",
                  "work3": "85",
                  "work4": "80",
                  "work5": "80",
                  "work6": "80"
            }, {
                  "id": "2015210405059",
                  "name": "林阳阳",
                  "class": "软工152",
                  "page": "https://lyyweb.github.io/",
                  "call1": "1",
                  "call2": "1",
                  "work1": "70",
                  "work2": "70",
                  "work3": "70",
                  "work4": "70",
                  "work5": "70",
                  "work6": "80"
            }, {
                  "id": "2015210405060",
                  "name": "朱勋韬",
                  "class": "软工152",
                  "page": "http://tftttt.github.io",
                  "call1": "0",
                  "call2": "0",
                  "work1": "0",
                  "work2": "0",
                  "work3": "0",
                  "work4": "0",
                  "work5": "0",
                  "work6": "0"
            }, {
                  "id": "2015210405061",
                  "name": "庄子遥",
                  "class": "软工152",
                  "page": "https://zhuangziyao.github.io",
                  "call1": "1",
                  "call2": "1",
                  "work1": "90",
                  "work2": "80",
                  "work3": "95",
                  "work4": "90",
                  "work5": "90",
                  "work6": "80"
            }, {
                  "id": "2015210405062",
                  "name": "张松鹏",
                  "class": "软工152",
                  "page": "http://zsp1079746899.github.io",
                  "call1": "1",
                  "call2": "1",
                  "work1": "80",
                  "work2": "80",
                  "work3": "60",
                  "work4": "70",
                  "work5": "70",
                  "work6": "80"
            }, {
                  "id": "2015210405063",
                  "name": "杨贺晨吉",
                  "class": "软工152",
                  "page": "http://aiduck.github.io",
                  "call1": "1",
                  "call2": "1",
                  "work1": "90",
                  "work2": "95",
                  "work3": "90",
                  "work4": "80",
                  "work5": "80",
                  "work6": "85"
            }, {
                  "id": "2015210405064",
                  "name": "张伟芳",
                  "class": "软工152",
                  "page": "http://zhangweifang2015210405064.github.io/",
                  "call1": "1",
                  "call2": "1",
                  "work1": "70",
                  "work2": "70",
                  "work3": "80",
                  "work4": "80",
                  "work5": "80",
                  "work6": "80"
            }, {
                  "id": "2015210405065",
                  "name": "滕飞",
                  "class": "软工152",
                  "page": "https://fantasticfbaby.github.io",
                  "call1": "1",
                  "call2": "1",
                  "work1": "80",
                  "work2": "80",
                  "work3": "90",
                  "work4": "90",
                  "work5": "80",
                  "work6": "80"
            }, {
                  "id": "2015210405066",
                  "name": "张银霞",
                  "class": "软工152",
                  "page": "http://fansofzyx.github.io/",
                  "call1": "1",
                  "call2": "1",
                  "work1": "80",
                  "work2": "70",
                  "work3": "90",
                  "work4": "90",
                  "work5": "80",
                  "work6": "80"
            }, {
                  "id": "2015210405067",
                  "name": "吴雨欣",
                  "class": "软工152",
                  "page": "http://wuyuxin2.github.io",
                  "call1": "1",
                  "call2": "1",
                  "work1": "60",
                  "work2": "70",
                  "work3": "60",
                  "work4": "80",
                  "work5": "80",
                  "work6": "80"
            }, {
                  "id": "2015210405068",
                  "name": "胡鑫",
                  "class": "软工152",
                  "page": "http://luoyinbinfen.github.io",
                  "call1": "1",
                  "call2": "1",
                  "work1": "80",
                  "work2": "70",
                  "work3": "70",
                  "work4": "90",
                  "work5": "80",
                  "work6": "80"
            }, {
                  "id": "2015210405069",
                  "name": "鲍文晗",
                  "class": "软工152",
                  "page": "http://baowh2015.github.io",
                  "call1": "1",
                  "call2": "1",
                  "work1": "80",
                  "work2": "70",
                  "work3": "80",
                  "work4": "90",
                  "work5": "80",
                  "work6": "85"
            }, {
                  "id": "2015210405070",
                  "name": "余宁宁",
                  "class": "软工152",
                  "page": "http://xunyiyu.github.io",
                  "call1": "1",
                  "call2": "1",
                  "work1": "80",
                  "work2": "70",
                  "work3": "85",
                  "work4": "90",
                  "work5": "90",
                  "work6": "80"
            }, {
                  "id": "2015210405071",
                  "name": "金茏晟",
                  "class": "软工152",
                  "page": "https://sillyking.github.io/",
                  "call1": "1",
                  "call2": "1",
                  "work1": "90",
                  "work2": "80",
                  "work3": "90",
                  "work4": "90",
                  "work5": "90",
                  "work6": "80"
            }, {
                  "id": "2015210405072",
                  "name": "姜晓红",
                  "class": "软工152",
                  "page": "http://little2366.github.io/",
                  "call1": "1",
                  "call2": "1",
                  "work1": "90",
                  "work2": "85",
                  "work3": "100",
                  "work4": "90",
                  "work5": "90",
                  "work6": "90"
            }, {
                  "id": "2015210405073",
                  "name": "邓悦",
                  "class": "软工152",
                  "page": "http://mercuryieafer.github.io",
                  "call1": "1",
                  "call2": "1",
                  "work1": "80",
                  "work2": "80",
                  "work3": "80",
                  "work4": "70",
                  "work5": "90",
                  "work6": "80"
            }, {
                  "id": "2015210405074",
                  "name": "陶瑜哲",
                  "class": "软工152",
                  "page": "http://tsummert.github.io/",
                  "call1": "1",
                  "call2": "1",
                  "work1": "80",
                  "work2": "80",
                  "work3": "70",
                  "work4": "90",
                  "work5": "85",
                  "work6": "80"
            }, {
                  "id": "2015210405075",
                  "name": "傅凯琪",
                  "class": "软工152",
                  "page": "https://dreamhuan.github.io/",
                  "call1": "1",
                  "call2": "1",
                  "work1": "70",
                  "work2": "80",
                  "work3": "90",
                  "work4": "95",
                  "work5": "100",
                  "work6": "95"
            }, {
                  "id": "2015210405076",
                  "name": "韦洁",
                  "class": "软工152",
                  "page": "https://nextinvitation.github.io/",
                  "call1": "1",
                  "call2": "1",
                  "work1": "60",
                  "work2": "80",
                  "work3": "85",
                  "work4": "90",
                  "work5": "80",
                  "work6": "80"
            }, {
                  "id": "2015210405077",
                  "name": "余煜淇",
                  "class": "软工152",
                  "page": "https://michelleleo.github.io",
                  "call1": "0",
                  "call2": "1",
                  "work1": "90",
                  "work2": "80",
                  "work3": "90",
                  "work4": "90",
                  "work5": "90",
                  "work6": "80"
            }, {
                  "id": "2015210405078",
                  "name": "周浩",
                  "class": "软工152",
                  "page": "https://riven19981221.github.io",
                  "call1": "0",
                  "call2": "0",
                  "work1": "0",
                  "work2": "0",
                  "work3": "0",
                  "work4": "0",
                  "work5": "0",
                  "work6": "0"
            }, {
                  "id": "2015210405079",
                  "name": "单德金",
                  "class": "软工152",
                  "page": "https://977878634.github.io/",
                  "call1": "1",
                  "call2": "1",
                  "work1": "90",
                  "work2": "80",
                  "work3": "90",
                  "work4": "90",
                  "work5": "90",
                  "work6": "80"
            }, {
                  "id": "2015211901105",
                  "name": "毛玲",
                  "class": "电子商务153",
                  "page": "https://oliviahussey.github.io/",
                  "call1": "1",
                  "call2": "1",
                  "work1": "80",
                  "work2": "80",
                  "work3": "60",
                  "work4": "90",
                  "work5": "80",
                  "work6": "80"
            }

      ]
}